<?xml version="1.0" ?><annotation verified="yes">
  <folder>Images</folder>
  <filename>000147.jpg</filename>
  <path>F:\Mydata\10.18\Images\000157.jpg</path>
  <source>
    <database>Unknown</database>
  </source>
  <size>
    <width>720</width>
    <height>960</height>
    <depth>3</depth>
  </size>
  <segmented>0</segmented>
  <object>
    <type>bndbox</type>
    <name>rice</name>
    <pose>Unspecified</pose>
    <truncated>0</truncated>
    <difficult>0</difficult>
    <bndbox>
      <xmin>363</xmin>
      <ymin>170</ymin>
      <xmax>470</xmax>
      <ymax>228</ymax>
    </bndbox>
  </object>
  <object>
    <type>bndbox</type>
    <name>rice</name>
    <pose>Unspecified</pose>
    <truncated>0</truncated>
    <difficult>0</difficult>
    <bndbox>
      <xmin>400</xmin>
      <ymin>270</ymin>
      <xmax>510</xmax>
      <ymax>332</ymax>
    </bndbox>
  </object>
  <object>
    <type>bndbox</type>
    <name>rice</name>
    <pose>Unspecified</pose>
    <truncated>0</truncated>
    <difficult>0</difficult>
    <bndbox>
      <xmin>314</xmin>
      <ymin>257</ymin>
      <xmax>385</xmax>
      <ymax>342</ymax>
    </bndbox>
  </object>
  <object>
    <type>bndbox</type>
    <name>rice</name>
    <pose>Unspecified</pose>
    <truncated>0</truncated>
    <difficult>0</difficult>
    <bndbox>
      <xmin>276</xmin>
      <ymin>166</ymin>
      <xmax>349</xmax>
      <ymax>256</ymax>
    </bndbox>
  </object>
  <object>
    <type>bndbox</type>
    <name>rice</name>
    <pose>Unspecified</pose>
    <truncated>0</truncated>
    <difficult>0</difficult>
    <bndbox>
      <xmin>208</xmin>
      <ymin>268</ymin>
      <xmax>274</xmax>
      <ymax>374</ymax>
    </bndbox>
  </object>
  <object>
    <type>bndbox</type>
    <name>rice</name>
    <pose>Unspecified</pose>
    <truncated>0</truncated>
    <difficult>0</difficult>
    <bndbox>
      <xmin>311</xmin>
      <ymin>376</ymin>
      <xmax>401</xmax>
      <ymax>447</ymax>
    </bndbox>
  </object>
  <object>
    <type>bndbox</type>
    <name>rice</name>
    <pose>Unspecified</pose>
    <truncated>0</truncated>
    <difficult>0</difficult>
    <bndbox>
      <xmin>125</xmin>
      <ymin>474</ymin>
      <xmax>225</xmax>
      <ymax>568</ymax>
    </bndbox>
  </object>
  <object>
    <type>bndbox</type>
    <name>rice</name>
    <pose>Unspecified</pose>
    <truncated>0</truncated>
    <difficult>0</difficult>
    <bndbox>
      <xmin>210</xmin>
      <ymin>747</ymin>
      <xmax>277</xmax>
      <ymax>908</ymax>
    </bndbox>
  </object>
  <object>
    <type>bndbox</type>
    <name>broken</name>
    <pose>Unspecified</pose>
    <truncated>0</truncated>
    <difficult>0</difficult>
    <bndbox>
      <xmin>299</xmin>
      <ymin>666</ymin>
      <xmax>384</xmax>
      <ymax>761</ymax>
    </bndbox>
  </object>
  <object>
    <type>bndbox</type>
    <name>broken</name>
    <pose>Unspecified</pose>
    <truncated>0</truncated>
    <difficult>0</difficult>
    <bndbox>
      <xmin>440</xmin>
      <ymin>604</ymin>
      <xmax>494</xmax>
      <ymax>645</ymax>
    </bndbox>
  </object>
  <object>
    <type>bndbox</type>
    <name>broken</name>
    <pose>Unspecified</pose>
    <truncated>0</truncated>
    <difficult>0</difficult>
    <bndbox>
      <xmin>413</xmin>
      <ymin>381</ymin>
      <xmax>471</xmax>
      <ymax>424</ymax>
    </bndbox>
  </object>
  <object>
    <type>bndbox</type>
    <name>broken</name>
    <pose>Unspecified</pose>
    <truncated>0</truncated>
    <difficult>0</difficult>
    <bndbox>
      <xmin>305</xmin>
      <ymin>477</ymin>
      <xmax>343</xmax>
      <ymax>530</ymax>
    </bndbox>
  </object>
  <object>
    <type>bndbox</type>
    <name>broken</name>
    <pose>Unspecified</pose>
    <truncated>0</truncated>
    <difficult>0</difficult>
    <bndbox>
      <xmin>161</xmin>
      <ymin>382</ymin>
      <xmax>200</xmax>
      <ymax>420</ymax>
    </bndbox>
  </object>
  <object>
    <type>bndbox</type>
    <name>broken</name>
    <pose>Unspecified</pose>
    <truncated>0</truncated>
    <difficult>0</difficult>
    <bndbox>
      <xmin>236</xmin>
      <ymin>598</ymin>
      <xmax>281</xmax>
      <ymax>650</ymax>
    </bndbox>
  </object>
  <object>
    <type>bndbox</type>
    <name>broken</name>
    <pose>Unspecified</pose>
    <truncated>0</truncated>
    <difficult>0</difficult>
    <bndbox>
      <xmin>145</xmin>
      <ymin>583</ymin>
      <xmax>199</xmax>
      <ymax>635</ymax>
    </bndbox>
  </object>
</annotation>