<?xml version="1.0" ?><annotation verified="yes">
  <folder>QQ_images</folder>
  <filename>000741.jpg</filename>
  <path>F:\Mydata\10.24\QQ_images\000752.jpg</path>
  <source>
    <database>Unknown</database>
  </source>
  <size>
    <width>960</width>
    <height>960</height>
    <depth>3</depth>
  </size>
  <segmented>0</segmented>
  <object>
    <type>bndbox</type>
    <name>broken</name>
    <pose>Unspecified</pose>
    <truncated>0</truncated>
    <difficult>0</difficult>
    <bndbox>
      <xmin>370</xmin>
      <ymin>495</ymin>
      <xmax>456</xmax>
      <ymax>584</ymax>
    </bndbox>
  </object>
  <object>
    <type>bndbox</type>
    <name>rice</name>
    <pose>Unspecified</pose>
    <truncated>0</truncated>
    <difficult>0</difficult>
    <bndbox>
      <xmin>85</xmin>
      <ymin>194</ymin>
      <xmax>211</xmax>
      <ymax>345</ymax>
    </bndbox>
  </object>
  <object>
    <type>bndbox</type>
    <name>rice</name>
    <pose>Unspecified</pose>
    <truncated>0</truncated>
    <difficult>0</difficult>
    <bndbox>
      <xmin>241</xmin>
      <ymin>208</ymin>
      <xmax>350</xmax>
      <ymax>363</ymax>
    </bndbox>
  </object>
  <object>
    <type>bndbox</type>
    <name>rice</name>
    <pose>Unspecified</pose>
    <truncated>0</truncated>
    <difficult>0</difficult>
    <bndbox>
      <xmin>401</xmin>
      <ymin>98</ymin>
      <xmax>482</xmax>
      <ymax>268</ymax>
    </bndbox>
  </object>
  <object>
    <type>bndbox</type>
    <name>rice</name>
    <pose>Unspecified</pose>
    <truncated>0</truncated>
    <difficult>0</difficult>
    <bndbox>
      <xmin>523</xmin>
      <ymin>13</ymin>
      <xmax>608</xmax>
      <ymax>208</ymax>
    </bndbox>
  </object>
  <object>
    <type>bndbox</type>
    <name>rice</name>
    <pose>Unspecified</pose>
    <truncated>0</truncated>
    <difficult>0</difficult>
    <bndbox>
      <xmin>575</xmin>
      <ymin>201</ymin>
      <xmax>673</xmax>
      <ymax>366</ymax>
    </bndbox>
  </object>
  <object>
    <type>bndbox</type>
    <name>rice</name>
    <pose>Unspecified</pose>
    <truncated>0</truncated>
    <difficult>0</difficult>
    <bndbox>
      <xmin>701</xmin>
      <ymin>328</ymin>
      <xmax>807</xmax>
      <ymax>488</ymax>
    </bndbox>
  </object>
  <object>
    <type>bndbox</type>
    <name>rice</name>
    <pose>Unspecified</pose>
    <truncated>0</truncated>
    <difficult>0</difficult>
    <bndbox>
      <xmin>357</xmin>
      <ymin>344</ymin>
      <xmax>521</xmax>
      <ymax>445</ymax>
    </bndbox>
  </object>
  <object>
    <type>bndbox</type>
    <name>rice</name>
    <pose>Unspecified</pose>
    <truncated>0</truncated>
    <difficult>0</difficult>
    <bndbox>
      <xmin>537</xmin>
      <ymin>419</ymin>
      <xmax>621</xmax>
      <ymax>590</ymax>
    </bndbox>
  </object>
  <object>
    <type>bndbox</type>
    <name>rice</name>
    <pose>Unspecified</pose>
    <truncated>0</truncated>
    <difficult>0</difficult>
    <bndbox>
      <xmin>76</xmin>
      <ymin>418</ymin>
      <xmax>251</xmax>
      <ymax>525</ymax>
    </bndbox>
  </object>
  <object>
    <type>bndbox</type>
    <name>rice</name>
    <pose>Unspecified</pose>
    <truncated>0</truncated>
    <difficult>0</difficult>
    <bndbox>
      <xmin>140</xmin>
      <ymin>642</ymin>
      <xmax>253</xmax>
      <ymax>823</ymax>
    </bndbox>
  </object>
  <object>
    <type>bndbox</type>
    <name>rice</name>
    <pose>Unspecified</pose>
    <truncated>0</truncated>
    <difficult>0</difficult>
    <bndbox>
      <xmin>355</xmin>
      <ymin>625</ymin>
      <xmax>472</xmax>
      <ymax>778</ymax>
    </bndbox>
  </object>
  <object>
    <type>bndbox</type>
    <name>rice</name>
    <pose>Unspecified</pose>
    <truncated>0</truncated>
    <difficult>0</difficult>
    <bndbox>
      <xmin>252</xmin>
      <ymin>850</ymin>
      <xmax>435</xmax>
      <ymax>949</ymax>
    </bndbox>
  </object>
  <object>
    <type>bndbox</type>
    <name>rice</name>
    <pose>Unspecified</pose>
    <truncated>0</truncated>
    <difficult>0</difficult>
    <bndbox>
      <xmin>579</xmin>
      <ymin>756</ymin>
      <xmax>689</xmax>
      <ymax>932</ymax>
    </bndbox>
  </object>
  <object>
    <type>bndbox</type>
    <name>rice</name>
    <pose>Unspecified</pose>
    <truncated>0</truncated>
    <difficult>0</difficult>
    <bndbox>
      <xmin>676</xmin>
      <ymin>697</ymin>
      <xmax>844</xmax>
      <ymax>842</ymax>
    </bndbox>
  </object>
  <object>
    <type>bndbox</type>
    <name>rice</name>
    <pose>Unspecified</pose>
    <truncated>0</truncated>
    <difficult>0</difficult>
    <bndbox>
      <xmin>663</xmin>
      <ymin>560</ymin>
      <xmax>844</xmax>
      <ymax>646</ymax>
    </bndbox>
  </object>
</annotation>