<?xml version="1.0" ?><annotation verified="yes">
  <folder>QQ_images</folder>
  <filename>001706.jpg</filename>
  <path>F:\Mydata\11.05\QQ_images\001717.jpg</path>
  <source>
    <database>Unknown</database>
  </source>
  <size>
    <width>960</width>
    <height>960</height>
    <depth>3</depth>
  </size>
  <segmented>0</segmented>
  <object>
    <type>bndbox</type>
    <name>rice</name>
    <pose>Unspecified</pose>
    <truncated>0</truncated>
    <difficult>0</difficult>
    <bndbox>
      <xmin>335</xmin>
      <ymin>80</ymin>
      <xmax>499</xmax>
      <ymax>173</ymax>
    </bndbox>
  </object>
  <object>
    <type>bndbox</type>
    <name>rice</name>
    <pose>Unspecified</pose>
    <truncated>0</truncated>
    <difficult>0</difficult>
    <bndbox>
      <xmin>56</xmin>
      <ymin>407</ymin>
      <xmax>239</xmax>
      <ymax>506</ymax>
    </bndbox>
  </object>
  <object>
    <type>bndbox</type>
    <name>rice</name>
    <pose>Unspecified</pose>
    <truncated>0</truncated>
    <difficult>0</difficult>
    <bndbox>
      <xmin>147</xmin>
      <ymin>604</ymin>
      <xmax>297</xmax>
      <ymax>724</ymax>
    </bndbox>
  </object>
  <object>
    <type>bndbox</type>
    <name>rice</name>
    <pose>Unspecified</pose>
    <truncated>0</truncated>
    <difficult>0</difficult>
    <bndbox>
      <xmin>443</xmin>
      <ymin>310</ymin>
      <xmax>630</xmax>
      <ymax>424</ymax>
    </bndbox>
  </object>
  <object>
    <type>bndbox</type>
    <name>rice</name>
    <pose>Unspecified</pose>
    <truncated>0</truncated>
    <difficult>0</difficult>
    <bndbox>
      <xmin>395</xmin>
      <ymin>720</ymin>
      <xmax>500</xmax>
      <ymax>907</ymax>
    </bndbox>
  </object>
  <object>
    <type>bndbox</type>
    <name>rice</name>
    <pose>Unspecified</pose>
    <truncated>0</truncated>
    <difficult>0</difficult>
    <bndbox>
      <xmin>549</xmin>
      <ymin>585</ymin>
      <xmax>722</xmax>
      <ymax>672</ymax>
    </bndbox>
  </object>
  <object>
    <type>bndbox</type>
    <name>rice</name>
    <pose>Unspecified</pose>
    <truncated>0</truncated>
    <difficult>0</difficult>
    <bndbox>
      <xmin>790</xmin>
      <ymin>490</ymin>
      <xmax>892</xmax>
      <ymax>629</ymax>
    </bndbox>
  </object>
  <object>
    <type>bndbox</type>
    <name>rice</name>
    <pose>Unspecified</pose>
    <truncated>0</truncated>
    <difficult>0</difficult>
    <bndbox>
      <xmin>764</xmin>
      <ymin>224</ymin>
      <xmax>865</xmax>
      <ymax>403</ymax>
    </bndbox>
  </object>
  <object>
    <type>bndbox</type>
    <name>broken</name>
    <pose>Unspecified</pose>
    <truncated>0</truncated>
    <difficult>0</difficult>
    <bndbox>
      <xmin>191</xmin>
      <ymin>215</ymin>
      <xmax>289</xmax>
      <ymax>306</ymax>
    </bndbox>
  </object>
  <object>
    <type>bndbox</type>
    <name>others</name>
    <pose>Unspecified</pose>
    <truncated>0</truncated>
    <difficult>0</difficult>
    <bndbox>
      <xmin>842</xmin>
      <ymin>878</ymin>
      <xmax>908</xmax>
      <ymax>931</ymax>
    </bndbox>
  </object>
</annotation>