<?xml version="1.0" ?><annotation verified="yes">
  <folder>QQ_images</folder>
  <filename>002340.jpg</filename>
  <path>F:\Mydata\11.08\QQ_images\002351.jpg</path>
  <source>
    <database>Unknown</database>
  </source>
  <size>
    <width>960</width>
    <height>960</height>
    <depth>3</depth>
  </size>
  <segmented>0</segmented>
  <object>
    <type>bndbox</type>
    <name>broken</name>
    <pose>Unspecified</pose>
    <truncated>0</truncated>
    <difficult>0</difficult>
    <bndbox>
      <xmin>201</xmin>
      <ymin>359</ymin>
      <xmax>297</xmax>
      <ymax>432</ymax>
    </bndbox>
  </object>
  <object>
    <type>bndbox</type>
    <name>broken</name>
    <pose>Unspecified</pose>
    <truncated>0</truncated>
    <difficult>0</difficult>
    <bndbox>
      <xmin>349</xmin>
      <ymin>541</ymin>
      <xmax>433</xmax>
      <ymax>605</ymax>
    </bndbox>
  </object>
  <object>
    <type>bndbox</type>
    <name>broken</name>
    <pose>Unspecified</pose>
    <truncated>0</truncated>
    <difficult>0</difficult>
    <bndbox>
      <xmin>726</xmin>
      <ymin>442</ymin>
      <xmax>812</xmax>
      <ymax>520</ymax>
    </bndbox>
  </object>
  <object>
    <type>bndbox</type>
    <name>rice</name>
    <pose>Unspecified</pose>
    <truncated>0</truncated>
    <difficult>0</difficult>
    <bndbox>
      <xmin>219</xmin>
      <ymin>155</ymin>
      <xmax>367</xmax>
      <ymax>218</ymax>
    </bndbox>
  </object>
  <object>
    <type>bndbox</type>
    <name>rice</name>
    <pose>Unspecified</pose>
    <truncated>0</truncated>
    <difficult>0</difficult>
    <bndbox>
      <xmin>508</xmin>
      <ymin>111</ymin>
      <xmax>614</xmax>
      <ymax>224</ymax>
    </bndbox>
  </object>
  <object>
    <type>bndbox</type>
    <name>rice</name>
    <pose>Unspecified</pose>
    <truncated>0</truncated>
    <difficult>0</difficult>
    <bndbox>
      <xmin>653</xmin>
      <ymin>192</ymin>
      <xmax>727</xmax>
      <ymax>318</ymax>
    </bndbox>
  </object>
  <object>
    <type>bndbox</type>
    <name>rice</name>
    <pose>Unspecified</pose>
    <truncated>0</truncated>
    <difficult>0</difficult>
    <bndbox>
      <xmin>544</xmin>
      <ymin>329</ymin>
      <xmax>667</xmax>
      <ymax>437</ymax>
    </bndbox>
  </object>
  <object>
    <type>bndbox</type>
    <name>rice</name>
    <pose>Unspecified</pose>
    <truncated>0</truncated>
    <difficult>0</difficult>
    <bndbox>
      <xmin>415</xmin>
      <ymin>266</ymin>
      <xmax>489</xmax>
      <ymax>419</ymax>
    </bndbox>
  </object>
  <object>
    <type>bndbox</type>
    <name>rice</name>
    <pose>Unspecified</pose>
    <truncated>0</truncated>
    <difficult>0</difficult>
    <bndbox>
      <xmin>435</xmin>
      <ymin>457</ymin>
      <xmax>569</xmax>
      <ymax>530</ymax>
    </bndbox>
  </object>
  <object>
    <type>bndbox</type>
    <name>rice</name>
    <pose>Unspecified</pose>
    <truncated>0</truncated>
    <difficult>0</difficult>
    <bndbox>
      <xmin>196</xmin>
      <ymin>584</ymin>
      <xmax>321</xmax>
      <ymax>683</ymax>
    </bndbox>
  </object>
  <object>
    <type>bndbox</type>
    <name>rice</name>
    <pose>Unspecified</pose>
    <truncated>0</truncated>
    <difficult>0</difficult>
    <bndbox>
      <xmin>393</xmin>
      <ymin>653</ymin>
      <xmax>537</xmax>
      <ymax>740</ymax>
    </bndbox>
  </object>
  <object>
    <type>bndbox</type>
    <name>rice</name>
    <pose>Unspecified</pose>
    <truncated>0</truncated>
    <difficult>0</difficult>
    <bndbox>
      <xmin>640</xmin>
      <ymin>660</ymin>
      <xmax>775</xmax>
      <ymax>781</ymax>
    </bndbox>
  </object>
</annotation>