<?xml version="1.0" ?><annotation verified="yes">
  <folder>QQ_images</folder>
  <filename>002413.jpg</filename>
  <path>F:\Mydata\11.08\QQ_images\002424.jpg</path>
  <source>
    <database>Unknown</database>
  </source>
  <size>
    <width>960</width>
    <height>960</height>
    <depth>3</depth>
  </size>
  <segmented>0</segmented>
  <object>
    <type>bndbox</type>
    <name>broken</name>
    <pose>Unspecified</pose>
    <truncated>0</truncated>
    <difficult>0</difficult>
    <bndbox>
      <xmin>383</xmin>
      <ymin>387</ymin>
      <xmax>431</xmax>
      <ymax>451</ymax>
    </bndbox>
  </object>
  <object>
    <type>bndbox</type>
    <name>broken</name>
    <pose>Unspecified</pose>
    <truncated>0</truncated>
    <difficult>0</difficult>
    <bndbox>
      <xmin>714</xmin>
      <ymin>234</ymin>
      <xmax>795</xmax>
      <ymax>294</ymax>
    </bndbox>
  </object>
  <object>
    <type>bndbox</type>
    <name>broken</name>
    <pose>Unspecified</pose>
    <truncated>0</truncated>
    <difficult>0</difficult>
    <bndbox>
      <xmin>807</xmin>
      <ymin>453</ymin>
      <xmax>883</xmax>
      <ymax>515</ymax>
    </bndbox>
  </object>
  <object>
    <type>bndbox</type>
    <name>rice</name>
    <pose>Unspecified</pose>
    <truncated>0</truncated>
    <difficult>0</difficult>
    <bndbox>
      <xmin>323</xmin>
      <ymin>136</ymin>
      <xmax>449</xmax>
      <ymax>239</ymax>
    </bndbox>
  </object>
  <object>
    <type>bndbox</type>
    <name>rice</name>
    <pose>Unspecified</pose>
    <truncated>0</truncated>
    <difficult>0</difficult>
    <bndbox>
      <xmin>232</xmin>
      <ymin>315</ymin>
      <xmax>332</xmax>
      <ymax>439</ymax>
    </bndbox>
  </object>
  <object>
    <type>bndbox</type>
    <name>rice</name>
    <pose>Unspecified</pose>
    <truncated>0</truncated>
    <difficult>0</difficult>
    <bndbox>
      <xmin>210</xmin>
      <ymin>519</ymin>
      <xmax>359</xmax>
      <ymax>587</ymax>
    </bndbox>
  </object>
  <object>
    <type>bndbox</type>
    <name>rice</name>
    <pose>Unspecified</pose>
    <truncated>0</truncated>
    <difficult>0</difficult>
    <bndbox>
      <xmin>531</xmin>
      <ymin>175</ymin>
      <xmax>647</xmax>
      <ymax>261</ymax>
    </bndbox>
  </object>
  <object>
    <type>bndbox</type>
    <name>rice</name>
    <pose>Unspecified</pose>
    <truncated>0</truncated>
    <difficult>0</difficult>
    <bndbox>
      <xmin>503</xmin>
      <ymin>319</ymin>
      <xmax>650</xmax>
      <ymax>394</ymax>
    </bndbox>
  </object>
  <object>
    <type>bndbox</type>
    <name>rice</name>
    <pose>Unspecified</pose>
    <truncated>0</truncated>
    <difficult>0</difficult>
    <bndbox>
      <xmin>643</xmin>
      <ymin>466</ymin>
      <xmax>748</xmax>
      <ymax>577</ymax>
    </bndbox>
  </object>
  <object>
    <type>bndbox</type>
    <name>rice</name>
    <pose>Unspecified</pose>
    <truncated>0</truncated>
    <difficult>0</difficult>
    <bndbox>
      <xmin>625</xmin>
      <ymin>640</ymin>
      <xmax>740</xmax>
      <ymax>761</ymax>
    </bndbox>
  </object>
  <object>
    <type>bndbox</type>
    <name>rice</name>
    <pose>Unspecified</pose>
    <truncated>0</truncated>
    <difficult>0</difficult>
    <bndbox>
      <xmin>411</xmin>
      <ymin>614</ymin>
      <xmax>514</xmax>
      <ymax>738</ymax>
    </bndbox>
  </object>
  <object>
    <type>bndbox</type>
    <name>rice</name>
    <pose>Unspecified</pose>
    <truncated>0</truncated>
    <difficult>0</difficult>
    <bndbox>
      <xmin>195</xmin>
      <ymin>673</ymin>
      <xmax>348</xmax>
      <ymax>751</ymax>
    </bndbox>
  </object>
</annotation>